LICENSE
MANIFEST.in
README.md
README.rst
setup.py
eyap/__init__.py
eyap.egg-info/PKG-INFO
eyap.egg-info/SOURCES.txt
eyap.egg-info/dependency_links.txt
eyap.egg-info/entry_points.txt
eyap.egg-info/requires.txt
eyap.egg-info/top_level.txt
eyap/core/__init__.py
eyap/core/comments.py
eyap/core/github_comments.py
eyap/core/redis_comments.py
eyap/core/yap_exceptions.py
eyap/scripts/__init__.py
eyap/scripts/egh.py
eyap/utils/__init__.py
eyap/utils/ghtools/__init__.py
eyap/utils/ghtools/gparse.py