Metadata-Version: 1.1
Name: eyap
Version: 0.9.3
Summary: Tools for extending yapping and comment management
Home-page: http://github.com/emin63/eyap
Author: Emin Martinian
Author-email: emin.martinian@gmail.com
License: custom
Keywords: comment management
Platform: UNKNOWN
Classifier: Development Status :: 3 - Alpha
Classifier: Intended Audience :: Developers
Classifier: Programming Language :: Python :: 3
